README.md
dotweet.py
setup.py
dotweet.egg-info/PKG-INFO
dotweet.egg-info/SOURCES.txt
dotweet.egg-info/dependency_links.txt
dotweet.egg-info/entry_points.txt
dotweet.egg-info/requires.txt
dotweet.egg-info/top_level.txt